dafne_models/__init__.py
dafne_models/common.py
dafne_models/bin/__init__.py
dafne_models/bin/create_model.py
dafne_models/resources/__init__.py
dafne_models/ui/ModelTrainer.py
dafne_models/ui/ModelTrainer_Ui.py
dafne_models/ui/__init__.py
dafne_models/utils/ThreadHelpers.py
dafne_models/utils/__init__.py
dafne_models/utils/source_tools.py
dafne_models-1.1.dist-info/LICENSE
dafne_models-1.1.dist-info/METADATA
dafne_models-1.1.dist-info/WHEEL
dafne_models-1.1.dist-info/entry_points.txt
dafne_models-1.1.dist-info/top_level.txt
dafne_models-1.1.dist-info/RECORD
