Metadata-Version: 2.1
Name: dafne-models
Version: 1.1
Summary: Deep Learning models module for Dafne
Home-page: https://github.com/dafne-imaging/dafne-models
Author: Francesco Santini
Author-email: francesco.santini@unibas.ch
Project-URL: Bug Tracker, https://github.com/dafne-imaging/dafne-model/issues
Classifier: Programming Language :: Python :: 3
Classifier: License :: OSI Approved :: GNU General Public License v3 or later (GPLv3+)
Classifier: Operating System :: OS Independent
Requires-Python: >=3.6
License-File: LICENSE
Requires-Dist: dafne-dl >=1.4a2
Requires-Dist: matplotlib
Provides-Extra: gui
Requires-Dist: PyQt5 ; extra == 'gui'
